[
  {
    "Sprache": "skt",
    "Vokabel": "ulūka-",
    "Übersetzungen": [
      {
        "Sprache": "eng",
        "Vokabel": "owl",
        "Quelle": "K",
        "Kapitel": "18",
        "Wortform": "m"
      },
      {
        "Sprache": "deu",
        "Vokabel": "Eule",
        "Quelle": "S"
      }
    ]
  },
  {
    "Sprache": "skt",
    "Vokabel": "pāntha-",
    "Übersetzungen": [
      {
        "Sprache": "deu",
        "Vokabel": "Reisender",
        "Quelle": "S"
      },
      {
        "Sprache": "deu",
        "Vokabel": "Wanderer",
        "Quelle": "S"
      }
    ]
  }
]